polang/__init__.py
polang/polars_expression_parser.py
polang-0.1.0.dist-info/METADATA
polang-0.1.0.dist-info/WHEEL
polang-0.1.0.dist-info/licenses/LICENSE
polang-0.1.0.dist-info/RECORD
