Metadata-Version: 2.1
Name: polang
Version: 0.1.0
Summary: Polang is a simple calulator language for polars data frames.
Project-URL: Homepage, https://github.com/AlexanderNenninger/polang
Author-email: Alexander Nenninger <alex.ne.dev@outlook.com>
License: MIT License
Classifier: License :: OSI Approved :: MIT License
Classifier: Operating System :: OS Independent
Classifier: Programming Language :: Python :: 3
Requires-Python: >=3.10
